tests/__init__.py
tests/test_asset.py
tests/test_mainnet_client.py
tests/test_ropsten_client.py
xchainpy_ethereum/__init__.py
xchainpy_ethereum/client.py
xchainpy_ethereum/crypto.py
xchainpy_ethereum/utils.py
xchainpy_ethereum/models/__init__.py
xchainpy_ethereum/models/asset.py
xchainpy_ethereum/resources/ERC20
xchainpy_ethereum/resources/ether_api
xchainpy_ethereum-0.2.1.dist-info/LICENSE
xchainpy_ethereum-0.2.1.dist-info/METADATA
xchainpy_ethereum-0.2.1.dist-info/WHEEL
xchainpy_ethereum-0.2.1.dist-info/top_level.txt
xchainpy_ethereum-0.2.1.dist-info/RECORD
