Metadata-Version: 2.1
Name: xchainpy-ethereum
Version: 0.2.1
Summary: Custom Ethereum client and utilities used by XChainPY clients
Home-page: https://github.com/xchainjs/xchainpy-lib/tree/main/xchainpy/xchainpy_ethereum
Author: THORChain
Author-email: 
License: MIT
Keywords: ETH,Ethereum,XChainpy_ethereum,THORChain,web3
Platform: UNKNOWN
Classifier: Intended Audience :: Developers
Classifier: Topic :: Software Development :: Libraries :: Python Modules
Classifier: License :: OSI Approved :: MIT License
Classifier: Programming Language :: Python :: 3
Classifier: Programming Language :: Python :: 3.6
Classifier: Programming Language :: Python :: 3.7
Classifier: Programming Language :: Python
Requires-Dist: web3 (>=5.16.0)
Requires-Dist: websockets (>=8.1)
Requires-Dist: xchainpy-client (>=0.1.3)
Requires-Dist: xchainpy-crypto (>=0.1.3)
Requires-Dist: faster-than-requests (>=20.10.19)
